dummy_transformations/__init__.py
dummy_transformations/transformations.py
dummy_transformations-0.4.1.dist-info/LICENSE
dummy_transformations-0.4.1.dist-info/WHEEL
dummy_transformations-0.4.1.dist-info/METADATA
dummy_transformations-0.4.1.dist-info/RECORD
